main.py
src/__init__.py
src/__main__.py
src/utilities.py
eopra_switcher-0.0.4.dist-info/LICENSE
eopra_switcher-0.0.4.dist-info/METADATA
eopra_switcher-0.0.4.dist-info/WHEEL
eopra_switcher-0.0.4.dist-info/entry_points.txt
eopra_switcher-0.0.4.dist-info/top_level.txt
eopra_switcher-0.0.4.dist-info/RECORD
